spotify_local.py
spotify_local/__init__.py
spotify_local/core.py
spotify_local/event.py
spotify_local/events.py
spotify_local/update_status.py
spotify_local_control-0.2.3.dist-info/METADATA
spotify_local_control-0.2.3.dist-info/RECORD
spotify_local_control-0.2.3.dist-info/WHEEL
spotify_local_control-0.2.3.dist-info/top_level.txt
